slurm_cola/__init__.py
slurm_cola/handler.py
slurm_cola/informations.py
slurm_cola/logwindow.py
slurm_cola/main.py
slurm_cola/mainwindow.py
slurm_cola-0.0.2.dist-info/LICENSE
slurm_cola-0.0.2.dist-info/METADATA
slurm_cola-0.0.2.dist-info/WHEEL
slurm_cola-0.0.2.dist-info/entry_points.txt
slurm_cola-0.0.2.dist-info/top_level.txt
slurm_cola-0.0.2.dist-info/RECORD
