Metadata-Version: 2.1
Name: slurm-cola
Version: 0.0.2
Summary: A tool to easily cancel slurm jobs belonging together
Home-page: https://github.com/cydanil/slurm-cola
Author: Cyril Danilevski
Author-email: cydanil@gmail.com
License: UNKNOWN
Platform: UNKNOWN
Classifier: Environment :: X11 Applications :: Qt
Classifier: Intended Audience :: Developers
Classifier: Intended Audience :: Science/Research
Classifier: License :: OSI Approved :: BSD License
Classifier: Operating System :: POSIX :: Linux
Classifier: Topic :: Scientific/Engineering
Requires-Python: >=3.6
Requires-Dist: PyQt5 (>=5.12.0)
